qiniu_cli/__init__.py
qiniu_cli/qiniu.py
qiniu_cli/cli.py
qiniu_cli-0.1.0.dist-info/top_level.txt
qiniu_cli-0.1.0.dist-info/metadata.json
qiniu_cli-0.1.0.dist-info/RECORD
qiniu_cli-0.1.0.dist-info/WHEEL
qiniu_cli-0.1.0.dist-info/DESCRIPTION.rst
qiniu_cli-0.1.0.dist-info/METADATA
qiniu_cli-0.1.0.dist-info/entry_points.txt
