Metadata-Version: 2.0
Name: qiniu-cli
Version: 0.1.0
Summary: CLI tool for Qiniu
Home-page: https://github.com/mozillazg/qiniu-cli
Author: mozillazg
Author-email: mozillazg101@gmail.com
License: MIT
Keywords: Qiniu,CLI
Platform: UNKNOWN
Classifier: Development Status :: 5 - Production/Stable
Classifier: Intended Audience :: Developers
Classifier: License :: OSI Approved :: MIT License
Classifier: Operating System :: OS Independent
Classifier: Programming Language :: Python
Classifier: Programming Language :: Python :: 2
Classifier: Programming Language :: Python :: 2.6
Classifier: Programming Language :: Python :: 2.7
Classifier: Programming Language :: Python :: 3
Classifier: Programming Language :: Python :: 3.3
Classifier: Programming Language :: Python :: 3.4
Classifier: Environment :: Console
Classifier: Topic :: Utilities
Classifier: Topic :: Terminals
Requires-Dist: Click
Requires-Dist: requests
